AUTHORS.txt
LICENSE-BSD.txt
MANIFEST.in
NOTICE.txt
README.rst
nose_regression.py
setup.py
nose_regression.egg-info/PKG-INFO
nose_regression.egg-info/SOURCES.txt
nose_regression.egg-info/dependency_links.txt
nose_regression.egg-info/entry_points.txt
nose_regression.egg-info/top_level.txt