Metadata-Version: 1.0
Name: nose-regression
Version: 1.0
Summary: A simple regression testing plugin for nose.
Home-page: http://packages.python.org/nose-regression
Author: Matt Luongo
Author-email: mhluongo@gmail.com
License: UNKNOWN
Platform: posix
Classifier: Intended Audience :: Developers
Classifier: License :: OSI Approved :: BSD License
Classifier: Operating System :: POSIX
Classifier: Programming Language :: Python
Classifier: Development Status :: 5 - Production/Stable
Classifier: Natural Language :: English
Classifier: Topic :: Software Development :: Bug Tracking
Classifier: Topic :: Software Development :: Testing
Classifier: Topic :: Software Development :: Quality Assurance
